Metadata-Version: 1.0
Name: distributions-something-interesting
Version: 0.1
Summary: Gaussian distributions
Home-page: UNKNOWN
Author: Carl Shi
Author-email: UNKNOWN
License: UNKNOWN
Platform: UNKNOWN
